setup.py
pyselog/__init__.py
pyselog/pyselog.py
pyselog/simplelog.py
pyselog.egg-info/PKG-INFO
pyselog.egg-info/SOURCES.txt
pyselog.egg-info/dependency_links.txt
pyselog.egg-info/top_level.txt