Metadata-Version: 1.0
Name: pyselog
Version: 0.0.3
Summary: This is a simple logger for python
Home-page: UNKNOWN
Author: Jeffrey Zhang
Author-email: 124303687@qq.com
License: MIT
Platform: UNKNOWN
